pytzsub/__init__.py
pytzsub/__main__.py
pytzsub/_version.py
pytzsub/fs.py
pytzsub/sub.py
pytzsub/zone-sub.tab
pytzsub-2020.6.dist-info/LICENSE
pytzsub-2020.6.dist-info/METADATA
pytzsub-2020.6.dist-info/WHEEL
pytzsub-2020.6.dist-info/top_level.txt
pytzsub-2020.6.dist-info/zip-safe
pytzsub-2020.6.dist-info/RECORD
