Metadata-Version: 2.1
Name: pytzsub
Version: 2020.6
Summary: World timezone definitions by country Subdivision (e.g., provinces or states)
Home-page: https://github.com/maxim-s-barabash/pytzsub
Author: Barabash Maxim
Author-email: maxim.s.barabash@gmail.com
Maintainer: Barabash Maxim
Maintainer-email: maxim.s.barabash@gmail.com
License: MIT License
Project-URL: Source, https://github.com/maxim-s-barabash/pytzsub
Project-URL: Tracker, https://github.com/maxim-s-barabash/pytzsub/issues
Keywords: timezone,tzinfo,datetime,pytz,time
Platform: Independent
Classifier: Development Status :: 4 - Beta
Classifier: Intended Audience :: Developers
Classifier: License :: OSI Approved :: MIT License
Classifier: Natural Language :: English
Classifier: Operating System :: OS Independent
Classifier: Programming Language :: Python
Classifier: Topic :: Software Development :: Libraries :: Python Modules
